improvelib/README.md
improvelib/__init__.py
improvelib/data_loader.py
improvelib/metrics.py
improvelib/split_generation.py
improvelib/utils.py
improvelib/Benchmarks/Base.py
improvelib/Benchmarks/Docking.py
improvelib/Benchmarks/drug_response_prediction.py
improvelib/Tests/Data/common_parameters.yml
improvelib/Tests/Data/default.cfg
improvelib/applications/__init__.py
improvelib/applications/drug_response_prediction/__init__.py
improvelib/applications/drug_response_prediction/common_parameters.yml
improvelib/applications/drug_response_prediction/config.py
improvelib/applications/drug_response_prediction/drp_utils.py
improvelib/applications/drug_response_prediction/drug_utils.py
improvelib/applications/drug_response_prediction/omics_utils.py
improvelib/initializer/__init__.py
improvelib/initializer/cli.py
improvelib/initializer/cli_params_def.py
improvelib/initializer/config.py
improvelib/initializer/stage_config.py
improvelib/workflow_utils/__init__.py
improvelib/workflow_utils/cross_study/README.md
improvelib/workflow_utils/cross_study/__init__.py
improvelib/workflow_utils/cross_study/csa_utils.py
improvelib/workflow_utils/learning_curve/__init__.py
improvelib-0.2.dist-info/LICENSE
improvelib-0.2.dist-info/METADATA
improvelib-0.2.dist-info/WHEEL
improvelib-0.2.dist-info/top_level.txt
improvelib-0.2.dist-info/RECORD
