Metadata-Version: 2.1
Name: improvelib
Version: 0.2
Summary: Within the IMPROVE project, we address some of the challenges around model comparisons, dataset standardization, and availability through the development and provision of a software framework. The goal is to make it routine practice for the broader community (cancer research and other areas) to compare new machine learning modeling approaches to previous models rigorously and comprehensively.
Author-email: Alex Partin <apartin@anl.gov>
Project-URL: Homepage, https://github.com/JDACS4C-IMPROVE/IMPROVE
Project-URL: Issues, https://github.com/JDACS4C-IMPROVE/IMPROVE/issues
Project-URL: Documentation, https://jdacs4c-improve.github.io/docs/
Classifier: Programming Language :: Python :: 3
Classifier: Programming Language :: Python :: 3.6
Classifier: Programming Language :: Python :: 3.7
Classifier: Programming Language :: Python :: 3.8
Classifier: License :: OSI Approved :: MIT License
Classifier: Operating System :: OS Independent
Classifier: Development Status :: 3 - Alpha
Classifier: Intended Audience :: Developers
Classifier: Topic :: Software Development :: Libraries
Requires-Python: >=3.6
License-File: LICENSE
Requires-Dist: pandas
Requires-Dist: requests
Requires-Dist: tqdm
Requires-Dist: typing-extensions
Requires-Dist: pyyaml
Requires-Dist: scikit-learn
